PygameGUI/Screen.py
PygameGUI/__init__.py
PygameGUI/Sprites/Button.py
PygameGUI/Sprites/Mat.py
PygameGUI/Sprites/Slider.py
PygameGUI/Sprites/Sprite.py
PygameGUI/Sprites/Text.py
PygameGUI/Sprites/__init__.py
PygameGUI/Sprites/Space3D/Space3D.py
PygameGUI/Sprites/Space3D/__init__.py
PygameGUI/Sprites/Space3D/fast_math.py
PygameGUI/Sprites/Space3D/matrix_functions.py
PygameGUI/Sprites/Space3D/projection.py
PygameGUI/Sprites/Space3D/Objects/Axis3D.py
PygameGUI/Sprites/Space3D/Objects/Camera.py
PygameGUI/Sprites/Space3D/Objects/Dot3D.py
PygameGUI/Sprites/Space3D/Objects/Hollow3D.py
PygameGUI/Sprites/Space3D/Objects/Object3D.py
PygameGUI/Sprites/Space3D/Objects/Solid3D.py
PygameGUI/Sprites/Space3D/Objects/__init__.py
PygameGUI/Sprites/Space3D/Objects/pre_settings.py
pygame_gui_by_zaskar-0.0.11.dist-info/LICENSE
pygame_gui_by_zaskar-0.0.11.dist-info/METADATA
pygame_gui_by_zaskar-0.0.11.dist-info/WHEEL
pygame_gui_by_zaskar-0.0.11.dist-info/top_level.txt
pygame_gui_by_zaskar-0.0.11.dist-info/RECORD
