Metadata-Version: 2.1
Name: pygame-gui-by-zaskar
Version: 0.0.11
Summary: some pygame widgets and 3d graphics
Author-email: ZaSKaR <mark.turkov@mail.ru>
Project-URL: Homepage, https://github.com/MarkT5/PygameGUI
Project-URL: Bug Tracker, https://github.com/MarkT5/PygameGUI/issues
Classifier: Programming Language :: Python :: 3
Classifier: Topic :: Software Development :: User Interfaces  
Classifier: Operating System :: OS Independent
Requires-Python: >=3.8
License-File: LICENSE
Requires-Dist: numba (>=0.50.0)
Requires-Dist: scipy (>=1.10.0)
